callbackframework.pyi
pyfbsdk.pyi
pyfbsdk_additions.pyi
motionbuilder_stubs-2026.1.0.dist-info/METADATA
motionbuilder_stubs-2026.1.0.dist-info/WHEEL
motionbuilder_stubs-2026.1.0.dist-info/licenses/LICENSE
motionbuilder_stubs-2026.1.0.dist-info/RECORD
