Metadata-Version: 2.4
Name: motionbuilder-stubs
Version: 2026.1.0
Summary: Stubs for Autodesk MotionBuilder's pyfbsdk api
Project-URL: Homepage, https://github.com/nils-soderman/pyfbsdk-stub-generator
Project-URL: Issues, https://github.com/nils-soderman/pyfbsdk-stub-generator/issues
Author: Nils Soderman
License-Expression: MIT-0
License-File: LICENSE
Keywords: autodesk,mobu,motionbuilder,pyfbsdk,stub
Classifier: Intended Audience :: Developers
Classifier: License :: OSI Approved :: MIT No Attribution License (MIT-0)
Classifier: Operating System :: OS Independent
Classifier: Programming Language :: Python :: 3
Classifier: Typing :: Stubs Only
Requires-Python: >=3.7
